Workbook
Name aporte: App!$D$22
Name patrimonio: App!$D$25
Name qtd_anos: App!$D$23
Name rendimento_carteira: App!$D$18
Name salario: App!$D$17
Name sugestao_investimento: App!$D$19
Name taxa_mensal: App!$D$24

Sheet App
B16: CONFIGURAÇÕES
B17: Salário | D17: 6784.77
B18: Rendimento Carteira | D18: 0.006
B19: Sugestão de investimento (30%) | D19: =D17*30% -> 2035.431
B21: INVESTIMENTO MENSAL
B22: Qual valor investir por mês? | D22: 1750
B23: Por quantos anos? | D23: 5
B24: Taxa de rendimento mensal | D24: 0.01079
B25: Patrimônio a acumular | D25: =FV(taxa_mensal,qtd_anos*12,aporte*-1) -> 146609.6
B26: Dividendos mensais | D26: =patrimonio*rendimento_carteira -> 879.6576
B29: CENÁRIOS | D29: DIVIDENDOS
A30: 2 | B30: Patrimônimo acumulado em 2 anos | C30: =FV(taxa_mensal,$A30*12,aporte*-1) -> 47648.348 | D30: =C30*rendimento_carteira -> 285.89009
A31: 5 | B31: Patrimônimo acumulado em 5 anos | C31: =FV(taxa_mensal,$A31*12,aporte*-1) -> 146609.6 | D31: =C31*rendimento_carteira -> 879.6576
A32: 10 | B32: Patrimônimo acumulado em 10 anos | C32: =FV(taxa_mensal,$A32*12,aporte*-1) -> 425747.37 | D32: =C32*rendimento_carteira -> 2554.4842
A33: 20 | B33: Patrimônimo acumulado em 20 anos | C33: =FV(taxa_mensal,$A33*12,aporte*-1) -> 1969097.2 | D33: =C33*rendimento_carteira -> 11814.583
A34: 30 | B34: Patrimônimo acumulado em 30 anos | C34: =FV(taxa_mensal,$A34*12,aporte*-1) -> 7563796.9 | D34: =C34*rendimento_carteira -> 45382.781
B37: Perfil | C37: Conservador
B38: VALOR A SER INVESTIDO POR MÊS | C38: =aporte -> 1750
B41: Tipo de FII | C41: Percentual Sugerido | D41: Valores
B42: PAPEL | C42: =VLOOKUP($C$37&"-"&B42,Tab_apoio_chave_composta!$A:$D,4,FALSE) -> 0.25 | D42: =$C$38*C42 -> 437.5
B43: TIJOLO | C43: =VLOOKUP($C$37&"-"&B43,Tab_apoio_chave_composta!$A:$D,4,FALSE) -> 0.5 | D43: =$C$38*C43 -> 875
B44: HÍBRIDO | C44: =VLOOKUP($C$37&"-"&B44,Tab_apoio_chave_composta!$A:$D,4,FALSE) -> 0.15 | D44: =$C$38*C44 -> 262.5
B45: FOFs | C45: =VLOOKUP($C$37&"-"&B45,Tab_apoio_chave_composta!$A:$D,4,FALSE) -> 0.06 | D45: =$C$38*C45 -> 105
B46: DESENVOLVIMENTO | C46: =VLOOKUP($C$37&"-"&B46,Tab_apoio_chave_composta!$A:$D,4,FALSE) -> 0.04 | D46: =$C$38*C46 -> 70
B47: HOTELARIAS | C47: =VLOOKUP($C$37&"-"&B47,Tab_apoio_chave_composta!$A:$D,4,FALSE) -> 0 | D47: =$C$38*C47 -> 0
C48: =SUM(C42:C47) -> 1 | D48: =SUM(D42:D47) -> 1750

Sheet Tab_apoio_chave_composta
A2: CHAVE | B2: PERFIL | C2: TIPO DE FII | D2: %
A3: =$B3&"-"&$C3 -> Conservador-PAPEL | B3: Conservador | C3: PAPEL | D3: 0.25
A4: =$B4&"-"&$C4 -> Conservador-TIJOLO | B4: Conservador | C4: TIJOLO | D4: 0.5
A5: =$B5&"-"&$C5 -> Conservador-HÍBRIDO | B5: Conservador | C5: HÍBRIDO | D5: 0.15
A6: =$B6&"-"&$C6 -> Conservador-FOFs | B6: Conservador | C6: FOFs | D6: 0.06
A7: =$B7&"-"&$C7 -> Conservador-DESENVOLVIMENTO | B7: Conservador | C7: DESENVOLVIMENTO | D7: 0.04
A8: =$B8&"-"&$C8 -> Conservador-HOTELARIAS | B8: Conservador | C8: HOTELARIAS | D8: 0
A9: =$B9&"-"&$C9 -> Moderado-PAPEL | B9: Moderado | C9: PAPEL | D9: 0.32
A10: =$B10&"-"&$C10 -> Moderado-TIJOLO | B10: Moderado | C10: TIJOLO | D10: 0.3
A11: =$B11&"-"&$C11 -> Moderado-HÍBRIDO | B11: Moderado | C11: HÍBRIDO | D11: 0.08
A12: =$B12&"-"&$C12 -> Moderado-FOFs | B12: Moderado | C12: FOFs | D12: 0.15
A13: =$B13&"-"&$C13 -> Moderado-DESENVOLVIMENTO | B13: Moderado | C13: DESENVOLVIMENTO | D13: 0.1
A14: =$B14&"-"&$C14 -> Moderado-HOTELARIAS | B14: Moderado | C14: HOTELARIAS | D14: 0.05
... A20: =$B20&"-"&$C20 -> Agressivo-HOTELARIAS | B20: Agressivo | C20: HOTELARIAS | D20: 0.1
